collateral/__init__.py
collateral/collateral.py
collateral/decorators.py
collateral/doctests.py
collateral/exception.py
collateral/functions.py
collateral/parameters.py
collateral/tools.py
collateral-1.0.6.dist-info/LICENSE
collateral-1.0.6.dist-info/METADATA
collateral-1.0.6.dist-info/WHEEL
collateral-1.0.6.dist-info/top_level.txt
collateral-1.0.6.dist-info/RECORD
