Metadata-Version: 2.1
Name: collateral
Version: 1.0.6
Summary: parallel object manipulation
Home-page: https://gitlab.limos.fr/brguillo/collateral
Author: Bruno Guillon
Author-email: bruno.guillon@uca.fr
License: MIT License
Platform: any
Classifier: Programming Language :: Python :: 3
Classifier: Development Status :: 3 - Alpha
Classifier: License :: OSI Approved :: MIT License
Classifier: Operating System :: OS Independent
Classifier: Topic :: Software Development :: Testing
License-File: LICENSE
